
[
    {
        "id": 1,
        "category": "Writing Genre",
        "description": "Strand units: Writing",
      "content": {
          "id": 0,
      "teaching": [
          {
                            "id": 0,
                            "topicTitle": "Introduction to Procedural Writing",
                            "topicContent": "  Introduce the concept of procedural writing and its purpose. Discuss how instructions and guides fall under this genre. Begin building vocabulary related to dental care."
                        },
                        {
                            "id": 1,
                            "topicTitle": "Identifying Sequencing",
                            "topicContent": "Emphasize the importance of clear sequencing in procedural writing. Present examples of step-by-step guides and ask students to identify the correct order of steps."
                        },
                        {
                            "id": 2,
                            "topicTitle": "Vocabulary for Dental Care",
                            "topicContent": " Introduce vocabulary related to dental hygiene, including toothbrush, toothpaste, floss, mouthwash, etc. Discuss how precise language is vital in procedural writing."
                        },
                        {
                            "id": 3,
                            "topicTitle": "Planning the Procedure",
                            "topicContent": "Explain the significance of planning before writing. Guide students in planning the procedure for brushing teeth, breaking it down into distinct steps. Use graphic organizers to help them structure their thoughts."
                        },
                        {
                            "id": 4,
                            "topicTitle": "Writing an Introduction",
                            "topicContent": "Teach students how to craft an engaging introduction for their procedure. Share examples of opening sentences and discuss how to set the context for the dental care process."
                    
                },
                {
                            "id": 5,
                            "topicTitle": "Sequencing the Steps",
                            "topicContent": "Guide students to write each step of the teeth brushing process in a logical sequence. Discuss the importance of using time-order words to guide readers through the steps."
                        },
                        {
                            "id": 6,
                            "topicTitle": "Adding Descriptive Details",
                            "topicContent": "Explain the significance of adding descriptive details to each step. Teach students how to use adjectives and adverbs to provide specific and clear instructions."
                        },
                        {
                            "id": 7,
                            "topicTitle": "Giving Clear Directions",
                            "topicContent": "Introduce imperative verbs (command verbs) commonly used in procedural writing. Discuss how starting each step with an imperative verb enhances clarity."
                        },
                        {
                            "id": 8,
                            "topicTitle": "Providing Time References",
                            "topicContent": "Teach students how to include time references in their instructions. Discuss the importance of specifying how long each step should take during teeth brushing."
                        },
                        {
                            "id": 9,
                            "topicTitle": "Writing a Conclusion",
                            "topicContent": "Explain how to conclude the procedural piece. Discuss how to summarize the process of brushing teeth and offer final tips or reminders."
                        },
                        {
                            "id": 10,
                            "topicTitle": "Editing and Sharing",
                            "topicContent": "Teach students the process of revising and editing their writing for clarity and accuracy. Focus on checking for capitalization, punctuation, and spelling errors. After editing, students can share their procedural pieces with peers."
                        }
                        
                    ]
                },
      "test": {
          "id": 0,
          "image": "testSwift",
          "time": "30 minutes",
          "description": "Put your Phonics and letter sound knowledge to the test.",
          "questions": [
             {
                    "id": 0,
                    "content": "Write a step-by-step guide on how to brush your teeth properly.",
                    "correctIndex": 0,
                    "answers": ["a", "b", "c", "d"]
                },
                {
                    "id": 1,
                    "content": "Create instructions for making a peanut butter and jelly sandwich. Include all the necessary steps.",
                    "correctIndex": 0,
                    "answers": ["a", "b", "c", "d"]
                },
                {
                    "id": 2,
                    "content": "Write a procedure for planting a flower seed in a pot. Describe each step in detail.",
                    "correctIndex": 0,
                    "answers": ["a", "b", "c", "d"]
                },
                {
                    "id": 3,
                    "content": "Provide a guide on how to build a simple paper airplane. Explain the folding and flying steps.",
                    "correctIndex": 0,
                    "answers": ["a", "b", "c", "d"]
                },
                {
                    "id": 4,
                    "content": "Write down the steps to create a colorful, hand-drawn birthday card for a friend or family member.",
                    "correctIndex": 0,
                    "answers": ["a", "b", "c", "d"]
                },
                {
                    "id": 5,
                    "content": "Give instructions on how to tie your shoelaces correctly. Include all the necessary details.",
                    "correctIndex": 0,
                    "answers": ["a", "b", "c", "d"]
                },
                {
                    "id": 6,
                    "content": "Create a step-by-step guide for setting up a picnic in the park, including what food to bring and how to arrange everything.",
                    "correctIndex": 0,
                    "answers": ["a", "b", "c", "d"]
                },
                {
                    "id": 7,
                    "content": "Provide instructions on how to build a simple LEGO structure, like a house or a car. Describe the building steps clearly.",
                    "correctIndex": 0,
                    "answers": ["a", "b", "c", "d"]
                },
                {
                    "id": 8,
                    "content": "Write a procedure for planting a vegetable garden in your backyard. Include soil preparation, planting, and care steps.",
                    "correctIndex": 0,
                    "answers": ["a", "b", "c", "d"]
                },
                {
                    "id": 9,
                    "content": "Give directions on how to make a cup of hot cocoa with marshmallows. Describe the process in order.",
                    "correctIndex": 0,
                    "answers": ["a", "b", "c", "d"]
                },
                
                {
                        "id": 10,
                        "content": "Write a step-by-step guide on how to make a simple paper boat and test it in a container of water.",
                        "correctIndex": 0,
                        "answers": ["a", "b", "c", "d"]
                    },
                    {
                        "id": 11,
                        "content": "Provide instructions on how to make a healthy fruit salad. List the fruits and the steps to prepare the salad.",
                        "correctIndex": 0,
                        "answers": ["a", "b", "c", "d"]
                    },
                    {
                        "id": 12,
                        "content": "Write down the steps to build a sandcastle at the beach, including tips for making it sturdy and detailed.",
                        "correctIndex": 0,
                        "answers": ["a", "b", "c", "d"]
                    },
                    {
                        "id": 13,
                        "content": "Create a procedure for setting up a bird feeder in your backyard. Explain how to fill it, hang it, and attract birds.",
                        "correctIndex": 0,
                        "answers": ["a", "b", "c", "d"]
                    },
                    {
                        "id": 14,
                        "content": "Give instructions on how to draw your favorite animal. Include the shapes and details to make it look realistic.",
                        "correctIndex": 0,
                        "answers": ["a", "b", "c", "d"]
                    },
                    {
                        "id": 15,
                        "content": "Write a step-by-step guide on how to make a delicious and colorful fruit smoothie. List the ingredients and blending process.",
                        "correctIndex": 0,
                        "answers": ["a", "b", "c", "d"]
                    },
                    {
                        "id": 16,
                        "content": "Provide instructions for building a small, recycled materials robot like WackyTron. Explain how to assemble it and what it can do.",
                        "correctIndex": 0,
                        "answers": ["a", "b", "c", "d"]
                    },
                    {
                        "id": 17,
                        "content": "Write down the steps to create a piece of art using different types of pasta. Explain how to glue them to make a design.",
                        "correctIndex": 0,
                        "answers": ["a", "b", "c", "d"]
                    },
                    {
                        "id": 18,
                        "content": "Give directions on how to build a simple, kid-friendly obstacle course in your backyard. Include the obstacles and how to navigate them.",
                        "correctIndex": 0,
                        "answers": ["a", "b", "c", "d"]
                    },
                    {
                        "id": 19,
                        "content": "Create a procedure for making a mini science experiment using baking soda and vinegar. Explain what happens and why.",
                        "correctIndex": 0,
                        "answers": ["a", "b", "c", "d"]
                    },
                    
                    {
                           "id": 20,
                           "content": "Write a step-by-step guide on how to plant a flower in a garden. Explain the tools, soil, and care needed for it to grow.",
                           "correctIndex": 0,
                           "answers": ["a", "b", "c", "d"]
                       },
                       {
                           "id": 21,
                           "content": "Provide instructions on how to create a colorful and informative poster for a school project. Include the materials and design tips.",
                           "correctIndex": 0,
                           "answers": ["a", "b", "c", "d"]
                       },
                       {
                           "id": 22,
                           "content": "Write down the steps to make a healthy and delicious homemade pizza. Include the dough, sauce, and toppings.",
                           "correctIndex": 0,
                           "answers": ["a", "b", "c", "d"]
                       },
                       {
                           "id": 23,
                           "content": "Create a procedure for making a creative and unique greeting card for a special occasion. Describe the design and message ideas.",
                           "correctIndex": 0,
                           "answers": ["a", "b", "c", "d"]
                       },
                       {
                           "id": 24,
                           "content": "Give directions on how to build a simple birdhouse for your backyard. Explain the measurements and painting options.",
                           "correctIndex": 0,
                           "answers": ["a", "b", "c", "d"]
                       },
                       {
                           "id": 25,
                           "content": "Write a step-by-step guide on how to make a kite and fly it successfully. Include materials and tips for launching.",
                           "correctIndex": 0,
                           "answers": ["a", "b", "c", "d"]
                       },
                       {
                           "id": 26,
                           "content": "Provide instructions on how to create a short dance routine. Describe the moves and music choices.",
                           "correctIndex": 0,
                           "answers": ["a", "b", "c", "d"]
                       },
                       {
                           "id": 27,
                           "content": "Write down the steps to make a colorful and tasty fruit popsicle. List the fruits and freezing process.",
                           "correctIndex": 0,
                           "answers": ["a", "b", "c", "d"]
                       },
                       {
                           "id": 28,
                           "content": "Create a procedure for setting up a mini science experiment using balloons and vinegar. Explain the chemical reaction and results.",
                           "correctIndex": 0,
                           "answers": ["a", "b", "c", "d"]
                       },
                       {
                           "id": 29,
                           "content": "Write a procedural writing piece on the topic of your your choice.",
                           "correctIndex": 0,
                           "answers": ["a", "b", "c", "d"]
                       }
                
                
               ]
               
               
               
               
               
          
      }
      
    }

]
