
[
    {
        "id": 0,
        "category": "Hand Writing ",
        "description": "Strand units: Writing",
      "content": {
          "id": 0,
      "teaching": [
         
                        {
                            "id": 0,
                            "topicTitle": "Lower case c",
                            "topicContent": "",
                            "video": "https://api-files.sproutvideo.com/file/0690d0b21716e0c78f/206ddfdeb56cfb2b/1080.mp4"
                        },
                        {
                            "id": 1,
                            "topicTitle": "Lower case o",
                            "topicContent": "",
                            "video": "https://api-files.sproutvideo.com/file/7090d0b21713e4c0f9/19549f142f4c2e34/1080.mp4"                         },
                        {
                            "id": 2,
                            "topicTitle": "Lower case a",
                            "topicContent": "",
                            "video": "https://api-files.sproutvideo.com/file/4490d0b21715e0cecd/5d9c00e5ee3bc231/1080.mp4"                         },
                        {
                            "id": 3,
                            "topicTitle": "Lower case d",
                            "topicContent": "",
                            "video": "https://api-files.sproutvideo.com/file/4d90d0b21710e4c2c4/205242ffe7d7f56e/1080.mp4"
                },
                {
                            "id": 4,
                            "topicTitle": "Lower case g",
                            "topicContent": "",
                    "video": "https://api-files.sproutvideo.com/file/7090d0b21712e4c1f9/b9f5dfc9c9c482ad/1080.mp4"                         },
                        {
                            "id": 5,
                            "topicTitle": "Lower case e",
                            "topicContent": ".",
                            "video": "https://api-files.sproutvideo.com/file/ac90d0b21711e0c225/f4663a9cc2054e07/1080.mp4"
                        },
                        {
                            "id": 6,
                            "topicTitle": "Lower case f",
                            "topicContent": "",
                            "video": "https://api-files.sproutvideo.com/file/0690d0b21711eece8f/a5413fe47e9d2962/1080.mp4"                         },
                        {
                            "id": 7,
                            "topicTitle": "Lower case s",
                            "topicContent": "",
                            "video": "https://api-files.sproutvideo.com/file/4490d0b21713e3cbcd/f338de2bf993f8e8/1080.mp4"                         },
                        {
                            "id": 8,
                            "topicTitle": "Lower case q",
                            "topicContent": "",
                            "video": "https://api-files.sproutvideo.com/file/7990d0b21713e1c0f0/7113133c02f0bd49/1080.mp4"                         },
                        {
                            "id": 9,
                            "topicTitle": "Lower case i",
                            "topicContent": "",
                            "video": "https://api-files.sproutvideo.com/file/d390d0b21712e6c45a/7e292bc74f89cae1/1080.mp4"                 },
                {
                            "id": 10,
                            "topicTitle": "Lower case r",
                            "topicContent": "",
                            "video": "https://api-files.sproutvideo.com/file/4d90d0b21713e0c5c4/82a9aa42648950e1/1080.mp4"
                        },
                        
                        {
                            "id": 11,
                            "topicTitle": "Lower case n",
                            "topicContent": "",
                            "video": "https://api-files.sproutvideo.com/file/0690d0b21918e7c08f/dfb1d090262d9003/1080.mp4"
                        },
                        {
                            "id": 12,
                            "topicTitle": "Lower case m",
                            "topicContent": "",
                            "video": "https://api-files.sproutvideo.com/file/ac90d0b21712edcc25/2b6528edbbaeda60/1080.mp4"
                        },
                       
                        {
                            "id": 13,
                            "topicTitle": "Lower case h",
                            "topicContent": "",
                            "video": "https://api-files.sproutvideo.com/file/ac90d0b21712e5c425/b5d48335177c19ed/1080.mp4"
                    
                },
                {
                            "id": 14,
                            "topicTitle": "Lower case b",
                            "topicContent": "",
                            "video": "https://api-files.sproutvideo.com/file/ac90d0b11515ebcc25/3cf5a48af4e410ae/1080.mp4"
                        },
                        {
                            "id": 15,
                            "topicTitle": "Lower case p",
                            "topicContent": "",
                            "video": "https://api-files.sproutvideo.com/file/4490d0b11515ebc4cd/e6fab57ead8307cc/1080.mp4"
                        },
                        {
                            "id": 16,
                            "topicTitle": "Lower case j",
                            "topicContent": "",
                            "video": "https://api-files.sproutvideo.com/file/ac90d0b21712e7c625/22d95fd483817bcd/1080.mp4"
                        },
                        
                        {
                            "id": 17,
                            "topicTitle": "Lower case l",
                            "topicContent": "",
                            "video": "https://api-files.sproutvideo.com/file/0690d0b21712e3c08f/3851721f817711e1/1080.mp4"                         },
                        {
                            "id": 18,
                            "topicTitle": "Lower case t",
                            "topicContent": "",
                            "video": "https://api-files.sproutvideo.com/file/7090d0b21713edc9f9/d2063720326344e6/1080.mp4"                         },
                        {
                            "id": 19,
                            "topicTitle": "Lower case k",
                            "topicContent": "",
                            "video": "https://api-files.sproutvideo.com/file/ea90d0b21712e0c763/af046b3e031905a0/1080.mp4"                         },
                        {
                            "id": 20,
                            "topicTitle": "Lower case u",
                            "topicContent": "",
                            "video": "https://api-files.sproutvideo.com/file/d390d0b2171cebc75a/39e9fce7cf647b31/1080.mp4"                 },
                {
                            "id": 21,
                            "topicTitle": "Lower case v",
                            "topicContent": "",
                            "video": "https://api-files.sproutvideo.com/file/1190d0b2171ce8ce98/167294acd2e9139f/1080.mp4"
                        },
                        
                        {
                            "id": 22,
                            "topicTitle": "Lower case w",
                            "topicContent": "",
                            "video": "https://api-files.sproutvideo.com/file/7090d0b2171ce9c2f9/1ea935ad9cef06ee/1080.mp4"
                        },
                        {
                            "id": 23,
                            "topicTitle": "Lower case y",
                            "topicContent": "",
                            "video": "https://api-files.sproutvideo.com/file/d390d0b2171cecc05a/ccaf461f3d8dc8e6/1080.mp4"
                        },
                       
                        {
                            "id": 24,
                            "topicTitle": "Lower case x",
                            "topicContent": "",
                            "video": "https://api-files.sproutvideo.com/file/4490d0b2171ceec9cd/f7583f61718488bf/1080.mp4"
                    
                },
                {
                            "id": 25,
                            "topicTitle": "Lower case z",
                            "topicContent": "",
                            "video": "https://api-files.sproutvideo.com/file/7090d0b2171cedc6f9/80fff6fc212950ed/1080.mp4"
                        }
                
                    ]
                },
      "test": {
      "id": 0,
      "image": "testSwift",
      "time": "30 minutes",
      "description": "Put your Phonics and letter sound knowledge to the test.",
      "questions": [
          {
               "id": 0,
               "content": "Write the letter 'a'",
               "correctIndex": 0,
               "answers": ["a", "b", "c", "d"]
           },
           {
               "id": 1,
               "content": "Write the letter 'b'",
               "correctIndex": 1,
               "answers": ["a", "b", "c", "d"]
           },
           {
               "id": 2,
               "content": "Write the letter 'c'",
               "correctIndex": 2,
               "answers": ["a", "b", "c", "d"]
           },
           {
               "id": 3,
               "content": "Write the letter 'd'",
               "correctIndex": 3,
               "answers": ["a", "b", "c", "d"]
           },
           {
               "id": 4,
               "content": "Write the letter 'e'",
               "correctIndex": 0,
               "answers": ["e", "f", "g", "h"]
           },
           {
               "id": 5,
               "content": "Write the letter 'f'",
               "correctIndex": 1,
               "answers": ["e", "f", "g", "h"]
           },
           {
               "id": 6,
               "content": "Write the letter 'g'",
               "correctIndex": 2,
               "answers": ["e", "f", "g", "h"]
           },
           {
               "id": 7,
               "content": "Write the letter 'h'",
               "correctIndex": 3,
               "answers": ["e", "f", "g", "h"]
           },
           {
               "id": 8,
               "content": "Write the letter 'i'",
               "correctIndex": 1,
               "answers": ["h", "i", "j", "k"]
           },
           {
               "id": 9,
               "content": "Write the letter 'j'",
               "correctIndex": 2,
               "answers": ["h", "i", "j", "k"]
           },
           {
               "id": 10,
               "content": "Write the letter 'k'",
               "correctIndex": 3,
               "answers": ["h", "i", "j", "k"]
           },
           {
               "id": 11,
               "content": "Write the letter 'l'",
               "correctIndex": 0,
               "answers": ["l", "m", "n", "o"]
           },
           {
               "id": 12,
               "content": "Write the letter 'm'",
               "correctIndex": 1,
               "answers": ["l", "m", "n", "o"]
           },
           {
               "id": 13,
               "content": "Write the letter 'n'",
               "correctIndex": 2,
               "answers": ["l", "m", "n", "o"]
           },
           {
               "id": 14,
               "content": "Write the letter 'o'",
               "correctIndex": 3,
               "answers": ["l", "m", "n", "o"]
           },
           {
               "id": 15,
               "content": "Write the letter 'p'",
               "correctIndex": 0,
               "answers": ["p", "q", "r", "s"]
           },
           {
               "id": 16,
               "content": "Write the letter 'q'",
               "correctIndex": 1,
               "answers": ["p", "q", "r", "s"]
           },
           {
               "id": 17,
               "content": "Write the letter 'r'",
               "correctIndex": 2,
               "answers": ["p", "q", "r", "s"]
           },
           {
               "id": 18,
               "content": "Write the letter 's'",
               "correctIndex": 3,
               "answers": ["p", "q", "r", "s"]
           },
           {
               "id": 19,
               "content": "Write the letter 't'",
               "correctIndex": 0,
               "answers": ["t", "u", "v", "w"]
           },
           {
               "id": 20,
               "content": "Write the letter 'u'",
               "correctIndex": 1,
               "answers": ["t", "u", "v", "w"]
           },
           {
               "id": 21,
               "content": "Write the letter 'v'",
               "correctIndex": 2,
               "answers": ["t", "u", "v", "w"]
           },
           {
               "id": 22,
               "content": "Write the letter 'w'",
               "correctIndex": 3,
               "answers": ["t", "u", "v", "w"]
           },
           {
               "id": 23,
               "content": "Write the letter 'x'",
               "correctIndex": 0,
               "answers": ["x", "y", "z", "A"]
           },
           {
               "id": 24,
               "content": "Write the letter 'y'",
               "correctIndex": 1,
               "answers": ["x", "y", "z", "A"]
           },
           {
               "id": 25,
               "content": "Write the letter 'z'",
               "correctIndex": 2,
               "answers": ["x", "y", "z", "A"]
           },
           {
               "id": 26,
               "content": "Write the letter 'A'",
               "correctIndex": 3,
               "answers": ["x", "y", "z", "A"]
           },
           {
               "id": 27,
               "content": "Write the letter 'B'",
               "correctIndex": 0,
               "answers": ["B", "C", "D", "E"]
           },
           {
               "id": 28,
               "content": "Write the letter 'C'",
               "correctIndex": 1,
               "answers": ["B", "C", "D", "E"]
           },
           {
               "id": 29,
               "content": "Write the letter 'D'",
               "correctIndex": 2,
               "answers": ["B", "C", "D", "E"]
           },
           {
               "id": 30,
               "content": "Write the letter 'E'",
               "correctIndex": 3,
               "answers": ["B", "C", "D", "E"]
           },
           {
               "id": 31,
               "content": "Write the letter 'F'",
               "correctIndex": 0,
               "answers": ["F", "G", "H", "I"]
           },
           {
               "id": 32,
               "content": "Write the letter 'G'",
               "correctIndex": 1,
               "answers": ["F", "G", "H", "I"]
           },
           {
               "id": 33,
               "content": "Write the letter 'H'",
               "correctIndex": 2,
               "answers": ["F", "G", "H", "I"]
           },
           {
               "id": 34,
               "content": "Write the letter 'I'",
               "correctIndex": 3,
               "answers": ["F", "G", "H", "I"]
           },
           {
               "id": 35,
               "content": "Write the letter 'J'",
               "correctIndex": 0,
               "answers": ["J", "K", "L", "M"]
           },
           {
               "id": 36,
               "content": "Write the letter 'K'",
               "correctIndex": 1,
               "answers": ["J", "K", "L", "M"]
           },
           {
               "id": 37,
               "content": "Write the letter 'L'",
               "correctIndex": 2,
               "answers": ["J", "K", "L", "M"]
           },
           {
               "id": 38,
               "content": "Write the letter 'M'",
               "correctIndex": 3,
               "answers": ["J", "K", "L", "M"]
           },
           {
               "id": 39,
               "content": "Write the letter 'N'",
               "correctIndex": 0,
               "answers": ["N", "O", "P", "Q"]
           },
           {
               "id": 40,
               "content": "Write the letter 'O'",
               "correctIndex": 1,
               "answers": ["N", "O", "P", "Q"]
           },
           {
               "id": 41,
               "content": "Write the letter 'P'",
               "correctIndex": 2,
               "answers": ["N", "O", "P", "Q"]
           },
           {
               "id": 42,
               "content": "Write the letter 'Q'",
               "correctIndex": 3,
               "answers": ["N", "O", "P", "Q"]
           },
           {
               "id": 43,
               "content": "Write the letter 'R'",
               "correctIndex": 0,
               "answers": ["R", "S", "T", "U"]
           },
           {
               "id": 44,
               "content": "Write the letter 'S'",
               "correctIndex": 1,
               "answers": ["R", "S", "T", "U"]
           },
           {
               "id": 45,
               "content": "Write the letter 'T'",
               "correctIndex": 2,
               "answers": ["R", "S", "T", "U"]
           },
           {
               "id": 46,
               "content": "Write the letter 'U'",
               "correctIndex": 3,
               "answers": ["R", "S", "T", "U"]
           },
           {
               "id": 47,
               "content": "Write the letter 'V'",
               "correctIndex": 0,
               "answers": ["V", "W", "X", "Y"]
           },
           {
               "id": 48,
               "content": "Write the letter 'W'",
               "correctIndex": 1,
               "answers": ["V", "W", "X", "Y"]
           },
           {
               "id": 49,
               "content": "Write the letter 'X'",
               "correctIndex": 2,
               "answers": ["V", "W", "X", "Y"]
           },
           {
               "id": 50,
               "content": "Write the letter 'Y'",
               "correctIndex": 3,
               "answers": ["V", "W", "X", "Y"]
           },
           {
               "id": 51,
               "content": "Write the letter 'Z'",
               "correctIndex": 0,
               "answers": ["Z", "A", "B", "C"]
           }
           ]
           
           
           

      }
    }

]
